ann_nmf/_ARDNMF_GEX.py
ann_nmf/__init__.py
ann_nmf/_supporting_functions/_MessageModule.py
ann_nmf/_supporting_functions/_add_nmf_results_to_adata.py
ann_nmf/_supporting_functions/_consensus_clustering.py
ann_nmf/_supporting_functions/_get_best_result.py
ann_nmf/_supporting_functions/_plot_signatures.py
ann_nmf/_supporting_functions/_prepare_NMF_inputs.py
ann_nmf/_supporting_functions/_run_ARD_NMF.py
ann_nmf/_utilities/__init__.py
ann_nmf/_utilities/_fetch_signature.py
ann_nmf/_utilities/_quick_dimension_reduce.py
ann_nmf/_utilities/_quick_norm_log_raw.py
ann_nmf/_utilities/_sklearn_compatibility.py
ann_nmf-0.0.1.dist-info/LICENSE
ann_nmf-0.0.1.dist-info/METADATA
ann_nmf-0.0.1.dist-info/WHEEL
ann_nmf-0.0.1.dist-info/top_level.txt
ann_nmf-0.0.1.dist-info/RECORD
