Metadata-Version: 2.1
Name: ann-nmf
Version: 0.0.1
Summary: ann_nmf - AnnData wrapper of the ARD-NMF module from SignatureAnalyzer
Home-page: https://github.com/mvinyard/ann_nmf
Author: Michael E. Vinyard - Harvard University - Massachussetts General Hospital - Broad Institute of MIT and Harvard
Author-email: mvinyard@broadinstitute.org
License: MIT
Platform: UNKNOWN
Classifier: Development Status :: 2 - Pre-Alpha
Classifier: Programming Language :: Python :: 3.6
Classifier: Intended Audience :: Science/Research
Classifier: Topic :: Scientific/Engineering :: Bio-Informatics
Requires-Python: >3.6.0
License-File: LICENSE
Requires-Dist: anndata (>=0.7.8)
Requires-Dist: matplotlib (>=3.5.1)
Requires-Dist: scanpy (>=1.8.2)
Requires-Dist: signatureanalyzer (>=0.0.7)
Requires-Dist: pandas (>=1.3.5)
Requires-Dist: pydk (>=0.0.4)
Requires-Dist: vinplots (>=0.0.43)
